{"imagen":"whatsapp.jpg","titulo":"Con esta aplicación podrás utilizar diferentes tipos de letras en WhatsApp","descripcion":"La tipografía de WhatsApp es bastante intuitiva y amigable, pero siempre nos gusta ir un paso adelante en la personalización de aplicaciones en el móvil.","nombre":"Elvin","apellidos":"Navas"}
{"imagen":"checo.jpg","titulo":"Checo inicia nueva era de Force India ","descripcion":"Sergio Pérez buscará su segundo podio de la temporada este domingo.","nombre":"Osiris","apellidos":"Perez"}
{"imagen":"galaxy.jpg","titulo":"HABRÍAN ENCONTRADO FANTASMAS DE UNIVERSOS ANTERIORES AL NUESTRO","descripcion":"Estamos solos o no?","nombre":"Melvin","apellidos":"Maldonado"}
{"imagen":"whatsapp.jpg","titulo":"Con esta aplicación podrás utilizar diferentes tipos de letras en WhatsApp","descripcion":"La tipografía de WhatsApp es bastante intuitiva y amigable, pero siempre nos gusta ir un paso adelante en la personalización de aplicaciones en el móvil.","nombre":"Elvin","apellidos":"Navas"}
{"imagen":"checo.jpg","titulo":"Checo inicia nueva era de Force India ","descripcion":"Sergio Pérez buscará su segundo podio de la temporada este domingo.","nombre":"Osiris","apellidos":"Perez"}
{"imagen":"galaxy.jpg","titulo":"HABRÍAN ENCONTRADO FANTASMAS DE UNIVERSOS ANTERIORES AL NUESTRO","descripcion":"Estamos solos o no?","nombre":"Melvin","apellidos":"Maldonado"}
